CONTRIBUTING.rst
MANIFEST.in
README.rst
setup.cfg
setup.py
django_report.egg-info/PKG-INFO
django_report.egg-info/SOURCES.txt
django_report.egg-info/dependency_links.txt
django_report.egg-info/not-zip-safe
django_report.egg-info/requires.txt
django_report.egg-info/top_level.txt
report/__init__.py
report/models.py
report/backends/__init__.py
report/backends/mining.py
report/management/__init__.py
report/management/commands/__init__.py
report/management/commands/update_report.py