Metadata-Version: 1.1
Name: django-report
Version: 0.1
Summary: Pluggable model report for Django.
Home-page: https://github.com/mining/django-report/
Author: Thiago Avelino
Author-email: thiago@avelino.xxx
License: UNKNOWN
Platform: UNKNOWN
Classifier: Environment :: Web Environment
Classifier: Framework :: Django
Classifier: Intended Audience :: Developers
Classifier: License :: OSI Approved :: MIT License
Classifier: Operating System :: OS Independent
Classifier: Programming Language :: Python
Classifier: Programming Language :: Python :: 2
Classifier: Programming Language :: Python :: 3
Classifier: Topic :: Utilities
